analog_nasbench-0.1.3.data/data/analog-nasbench/data.anb
analognasbench/__init__.py
analognasbench/data.anb
analognasbench/data.py
analog_nasbench-0.1.3.dist-info/METADATA
analog_nasbench-0.1.3.dist-info/WHEEL
analog_nasbench-0.1.3.dist-info/top_level.txt
analog_nasbench-0.1.3.dist-info/RECORD
