Metadata-Version: 2.2
Name: analog-nasbench
Version: 0.1.3
Requires-Dist: pandas
Requires-Dist: numpy
Dynamic: requires-dist
